{
  "type": "sophisticatedbackpacks:backpack_upgrade",
  "conditions": [
    {
      "type": "sophisticatedcore:item_enabled",
      "itemRegistryName": "sophisticatedbackpacks:gold_backpack"
    }
  ],
  "key": {
    "B": {
      "item": "sophisticatedbackpacks:iron_backpack"
    },
    "F": {
      "item": "zombie_fabrics:fabric_block"
    },
    "G": {
      "tag": "forge:storage_blocks/gold"
    }
  },
  "pattern": [
    "FGF",
    "GBG",
    "FGF"
  ],
  "result": {
    "item": "sophisticatedbackpacks:gold_backpack"
  }
}