{
  "type": "minecraft:crafting_shapeless",
  "category": "building",
  "group": "bonfires",
  "ingredients": [
    {
      "tag": "forge:ash"
    },
    {
      "tag": "forge:ash"
    },
    {
      "tag": "forge:ash"
    },
    {
      "tag": "forge:ash"
    },
    {
      "tag": "forge:ash"
    },
    {
      "tag": "forge:ash"
    },
    {
      "tag": "forge:ash"
    },
    {
      "tag": "forge:ash"
    },
    {
      "tag": "forge:ash"
    }
  ],
  "result": {
    "item": "bonfires:ash_block"
  }
}