
{
  "id": "ghostly",
  "key": "refinement.armor.ghostly",
  "incompat": ["ghostly"],
  "type": ["chest"],
  "proficiency_cost": 100,
  "material": "hmag:soul_powder",
  "material_count": 5,
  "anvil_levels": 5,
  "bonuses": [
	{
      "property": "attributeslib:dodge_chance",
      "amount": 0.05,
      "operation": "addition"
    },
	{
      "property": "minecraft:generic.attack_speed",
      "amount": -0.10,
      "operation": "multiply_total"
    }
  ],
  "allowed_steps": [1, 2, 3, 4, 5, 6, 7, 8, 9, 10],
  "color": "gray"
}